anyparser_core/__init__.py
anyparser_core/config/hardcoded.py
anyparser_core/form.py
anyparser_core/options.py
anyparser_core/parser.py
anyparser_core/py.typed
anyparser_core/request.py
anyparser_core/validator/__init__.py
anyparser_core/validator/main.py
anyparser_core/validator/option.py
anyparser_core/validator/path.py
anyparser_core/validator/url.py
anyparser_core/validator/validation.py
anyparser_core/version.py
anyparser_core-1.0.2.dist-info/LICENSE.md
anyparser_core-1.0.2.dist-info/METADATA
anyparser_core-1.0.2.dist-info/WHEEL
anyparser_core-1.0.2.dist-info/RECORD
