Metadata-Version: 2.3
Name: anyparser-core
Version: 1.0.2
Summary: Anyparser SDK for Python
License: Apache-2.0
Requires-Python: >=3.9
Classifier: Programming Language :: Python :: 3
Classifier: License :: OSI Approved :: Apache Software License
Classifier: Operating System :: OS Independent
Classifier: Typing :: Typed
Project-URL: Homepage, https://github.com/anyparser/anyparser_core
